ndx_events/__init__.py
ndx_events/events.py
ndx_events/io/__init__.py
ndx_events/io/events.py
ndx_events/spec/ndx-events.extensions.yaml
ndx_events/spec/ndx-events.namespace.yaml
tests/__init__.py
tests/test_example_usage.py
tests/integration/__init__.py
tests/integration/hdf5/__init__.py
tests/integration/hdf5/test_events.py
tests/unit/__init__.py
tests/unit/test_events.py
ndx_events-0.2.1.dist-info/LICENSE.txt
ndx_events-0.2.1.dist-info/METADATA
ndx_events-0.2.1.dist-info/WHEEL
ndx_events-0.2.1.dist-info/top_level.txt
ndx_events-0.2.1.dist-info/RECORD
