Metadata-Version: 2.2
Name: ndx-events
Version: 0.2.1
Summary: NWB extension for storing timestamped event and TTL pulse data
Home-page: https://github.com/rly/ndx-events
Author: Ryan Ly
Author-email: rly@lbl.gov
License: BSD 3-Clause
Classifier: Intended Audience :: Developers
Classifier: Intended Audience :: Science/Research
License-File: LICENSE.txt
Requires-Dist: pynwb>=1.1.2
Dynamic: author
Dynamic: author-email
Dynamic: classifier
Dynamic: description
Dynamic: description-content-type
Dynamic: home-page
Dynamic: license
Dynamic: requires-dist
Dynamic: summary
